Metadata-Version: 2.1
Name: llava-torch
Version: 1.2.2.post1
Summary: Towards GPT-4 like large language and visual assistant.
Project-URL: Homepage, https://llava-vl.github.io
Project-URL: Bug Tracker, https://github.com/haotian-liu/LLaVA/issues
Classifier: Programming Language :: Python :: 3
Classifier: License :: OSI Approved :: Apache Software License
Requires-Python: >=3.8
License-File: LICENSE
Requires-Dist: torch ==2.0.1
Requires-Dist: torchvision ==0.15.2
Requires-Dist: transformers ==4.36.2
Requires-Dist: tokenizers ==0.15.0
Requires-Dist: sentencepiece ==0.1.99
Requires-Dist: shortuuid
Requires-Dist: accelerate ==0.21.0
Requires-Dist: peft ==0.4.0
Requires-Dist: bitsandbytes ==0.41.0
Requires-Dist: pydantic
Requires-Dist: markdown2[all]
Requires-Dist: numpy
Requires-Dist: scikit-learn ==1.2.2
Requires-Dist: gradio ==4.16.0
Requires-Dist: gradio-client ==0.8.1
Requires-Dist: requests
Requires-Dist: httpx ==0.24.0
Requires-Dist: uvicorn
Requires-Dist: fastapi
Requires-Dist: einops ==0.6.1
Requires-Dist: einops-exts ==0.0.4
Requires-Dist: timm ==0.6.13
Provides-Extra: build
Requires-Dist: build ; extra == 'build'
Requires-Dist: twine ; extra == 'build'
Provides-Extra: train
Requires-Dist: deepspeed ==0.12.6 ; extra == 'train'
Requires-Dist: ninja ; extra == 'train'
Requires-Dist: wandb ; extra == 'train'
